<?xml version="1.0" encoding="UTF-8" ?>
<odoo>
    <data noupdate="1">
        <record id="send_employee_notification_cron" model="ir.cron">
            <field name="name">Send Employee Notification</field>
            <field name="interval_number">15</field>
            <field name="interval_type">minutes</field>
            <field name="numbercall">-1</field>
            <field name="active" eval="True"/>
            <field name="model_id" ref="model_hr_employee"/>
            <field name="state">code</field>
            <field name="code">model.create_employee_notification()</field>
        </record>
    </data>
</odoo>